{
  "headline": "Wohnen\ndarf nicht\nLuxus\nsein",
  "cta": "Jetzt Petition unterschreiben!",
  "stoerer": "Leist-\nbares\nWohnen",
  "body": "Mieten explodieren, Eigentum ist für viele unerreichbar. Wir wollen mehr geförderten Wohnbau, Mietobergrenzen und einen Stopp der Spekulation mit Wohnraum. Wohnen ist ein Grundrecht, kein Geschäftsmodell.",
  "social": "Facebook: gruene.noe\nInstagram: @gruene_noe\noffice@gruene-noe.at\n02742 / 90 230",
  "url": "https://gruene.at/leistbares-wohnen",
  "impressum": "Impressum: Medieninhaber und Herausgeber: Die Grünen Niederösterreich, Daniel-Gran-Straße 48, 3100 St. Pölten. · Druck: Druckerei mit Postanschrift · Evtl. Hinweis auf Umweltzeichen wenn zutreffend"
}
